nyan_ext_translate/__init__.py
nyan_ext_translate/translate.py
nyan_ext_translate-0.2.0.dist-info/METADATA
nyan_ext_translate-0.2.0.dist-info/WHEEL
nyan_ext_translate-0.2.0.dist-info/RECORD
