Metadata-Version: 2.1
Name: nyan-ext-translate
Version: 0.2.0
Summary: 
Author: sserve-kr
Author-email: personal@sserve.me
Requires-Python: >=3.10,<4.0
Classifier: Programming Language :: Python :: 3
Classifier: Programming Language :: Python :: 3.10
Classifier: Programming Language :: Python :: 3.11
Requires-Dist: nyanlang (>=1.3.5,<2.0.0)
